[
  {
    "id": "01J1NXC0GY18SWWPD76HFR6VM5",
    "name": "Tiler",
    "organization": "01J1NXHACY1WEKTFVS6GPDC20X",
    "department": null,
    "team": null
  },
  {
    "id": "01J1NXC0GZXAMRWR3SVWWE7XMY",
    "name": "Roma",
    "organization": "01J1NXHACY1WEKTFVS6GPDC20X",
    "department": "01J1NYCH7VTYKN364QGRXJ111R",
    "team": null
  },
  {
    "id": "01J1NXC0H0T2A18VMW7WYMGKY2",
    "name": "Kelwin",
    "organization": "01J1NXHACY1WEKTFVS6GPDC20X",
    "department": "01J1NYCH7WG9A5A6GH46MV7T2V",
    "team": null
  },
  {
    "id": "01J1NXC0H0V4WRVNY4AQX79WEY",
    "name": "Lebbie",
    "organization": "01J1NXHACY1WEKTFVS6GPDC20X",
    "department": "01J1NYCH7VTYKN364QGRXJ111R",
    "team": "01J1NYDTTB7N2XKWVTHP4RD9ZT"
  },
  {
    "id": "01J1NXC0H1QYGYZMTZK8YXN1Q7",
    "name": "Ninette",
    "organization": "01J1NXHACY1WEKTFVS6GPDC20X",
    "department": "01J1NYCH7VTYKN364QGRXJ111R",
    "team": "01J1NYDTTDNNC2GCG2GX83FTM1"
  },
  {
    "id": "01J1NXC0H23NK2QPST3DC22BNQ",
    "name": "Maurits",
    "organization": "01J1NXHACY1WEKTFVS6GPDC20X",
    "department": "01J1NYCH7WG9A5A6GH46MV7T2V",
    "team": "01J1NYDTTFXQKMKV3FETFD9NF0"
  },
  {
    "id": "01J1NXC0H203KGPZZEHAGSD5VA",
    "name": "Malena",
    "organization": "01J1NXHACY1WEKTFVS6GPDC20X",
    "department": "01J1NYCH7WG9A5A6GH46MV7T2V",
    "team": "01J1NYDTTG23WAJ8JPQBTQ2HKH"
  },
  {
    "id": "01J1NXC0H3VZ3TBVEZFNX5AYMK",
    "name": "Jordana",
    "organization": "01J1NXHACY1WEKTFVS6GPDC20X",
    "department": "01J1NYCH7VTYKN364QGRXJ111R",
    "team": "01J1NYDTTB7N2XKWVTHP4RD9ZT"
  },
  {
    "id": "01J1NXC0H4FB7ZHXFTDHGVZVCA",
    "name": "Josefa",
    "organization": "01J1NXHACY1WEKTFVS6GPDC20X",
    "department": "01J1NYCH7VTYKN364QGRXJ111R",
    "team": "01J1NYDTTDNNC2GCG2GX83FTM1"
  },
  {
    "id": "01J1NXC0H4J7NAR64PYD05Y0KX",
    "name": "Yolane",
    "organization": "01J1NXHACY1WEKTFVS6GPDC20X",
    "department": "01J1NYCH7VTYKN364QGRXJ111R",
    "team": "01J1NYDTTDNNC2GCG2GX83FTM1"
  },
  {
    "id": "01J1NXC0H5MKD81F4YGDR3JWEQ",
    "name": "Nolan",
    "organization": "01J1NXHACY1WEKTFVS6GPDC20X",
    "department": "01J1NYCH7VTYKN364QGRXJ111R",
    "team": "01J1NYDTTB7N2XKWVTHP4RD9ZT"
  },
  {
    "id": "01J1NXC0H682BH27YA6ZV8RKQZ",
    "name": "Aleece",
    "organization": "01J1NXHACY1WEKTFVS6GPDC20X",
    "department": "01J1NYCH7WG9A5A6GH46MV7T2V",
    "team": "01J1NYDTTG23WAJ8JPQBTQ2HKH"
  },
  {
    "id": "01J1NXC0H6GG57ABWFXPS3P93G",
    "name": "Sigfrid",
    "organization": "01J1NXHACY1WEKTFVS6GPDC20X",
    "department": "01J1NYCH7WG9A5A6GH46MV7T2V",
    "team": "01J1NYDTTFXQKMKV3FETFD9NF0"
  },
  {
    "id": "01J1NXC0H7SEJPPRGE2SWCWG12",
    "name": "Allsun",
    "organization": "01J1NXHACY1WEKTFVS6GPDC20X",
    "department": "01J1NYCH7WG9A5A6GH46MV7T2V",
    "team": "01J1NYDTTFXQKMKV3FETFD9NF0"
  },
  {
    "id": "01J1NXC0H8DX6TD5YDYSQFXK8Y",
    "name": "Dulci",
    "organization": "01J1NXHACY1WEKTFVS6GPDC20X",
    "department": "01J1NYCH7VTYKN364QGRXJ111R",
    "team": "01J1NYDTTB7N2XKWVTHP4RD9ZT"
  },
  {
    "id": "01J1NXC0H95A6YMS1K1S833TR4",
    "name": "Fidelio",
    "organization": "01J1NXHACY1WEKTFVS6GPDC20X",
    "department": "01J1NYCH7VTYKN364QGRXJ111R",
    "team": "01J1NYDTTDNNC2GCG2GX83FTM1"
  },
  {
    "id": "01J1NXC0H9C9J64AHVSYJ9MVGJ",
    "name": "Aubrey",
    "organization": "01J1NXHACY1WEKTFVS6GPDC20X",
    "department": "01J1NYCH7VTYKN364QGRXJ111R",
    "team": "01J1NYDTTDNNC2GCG2GX83FTM1"
  },
  {
    "id": "01J1NXC0HAC34NT740DB1J3ETP",
    "name": "Aime",
    "organization": "01J1NXHACY1WEKTFVS6GPDC20X",
    "department": "01J1NYCH7WG9A5A6GH46MV7T2V",
    "team": "01J1NYDTTG23WAJ8JPQBTQ2HKH"
  },
  {
    "id": "01J1NXC0HB50HD3JSV1KJ86TM6",
    "name": "Dulcine",
    "organization": "01J1NXHACY1WEKTFVS6GPDC20X",
    "department": "01J1NYCH7WG9A5A6GH46MV7T2V",
    "team": "01J1NYDTTFXQKMKV3FETFD9NF0"
  },
  {
    "id": "01J1NXC0HBMDF0SK1W2WBV03V2",
    "name": "Cash",
    "organization": "01J1NXHACY1WEKTFVS6GPDC20X",
    "department": "01J1NYCH7VTYKN364QGRXJ111R",
    "team": "01J1NYDTTDNNC2GCG2GX83FTM1"
  }
]
